<?xml version="1.0" encoding="UTF-8"?>
<relnotes name="Multimode TSY">
  <purpose>
    ETel TSY reference plugin for Multimode i.e. phones capable of accesing both GSM and GPRS networks. Replaced on an actual device by a hardware specific licensee TSY.
  </purpose>

  <defect number="PDEF118485" title="Klocwork issues, NULL pointer can be used in release build telephony_cdmatsy" revision="007">
    Improved handling of OOM conditions in CCallHayes
  </defect>
  
  <defect number="PDEF114689" title="Klocwork issues in mmtsy and simtsy" revision="006">
    Removed a redundant condition check in CATCommands::Complete()
  </defect>

  <defect number="PDEF102623" title="MM.TSY panics on machines with no COMM::0" revision="005">
    Fixed an MMTSY panic in machines with no COMM::0 port
  </defect>

  <defect number="DEF100530" title="SAN : Making a data call from PhoneUI returns TimedOut Error" revision="004">
    Fixed a problem in MMTSY initialisation
  </defect>

  <defect number="DEF099031" title="Unhandled exception in MM.TSY when MultimodeInitL() leaves" revision="003">
    Exception in MultimodeInitL is now handled correctly
  </defect>

  <defect number="DEF087681" title="MMTSY does not support RMobilePhone::GetPhoneStoreInfo with 4 parameters" revision="002">
    Support has been added for RMobilePhone::GetPhoneStoreInfo with 4 parameters
  </defect>

  <defect number="DEF087412" title="MMTSY panics when phonebook entry names are passed that are too long..." revision="001">
    Overflow condition now checked for long phonebook entry names
  </defect>
</relnotes>
